speedbeaver/__init__.py
speedbeaver/common.py
speedbeaver/config.py
speedbeaver/handlers.py
speedbeaver/methods.py
speedbeaver/middleware.py
speedbeaver/opentelemetry.py
speedbeaver/processor_collection_builder.py
speedbeaver-0.2.1.dist-info/METADATA
speedbeaver-0.2.1.dist-info/WHEEL
speedbeaver-0.2.1.dist-info/RECORD
