Metadata-Version: 2.4
Name: speedbeaver
Version: 0.2.1
Summary: Setting up logging for FastAPI should not take up the bulk of your time.
Requires-Python: >=3.10
Requires-Dist: asgi-correlation-id>=4.3.4
Requires-Dist: fastapi>=0.115.12
Requires-Dist: orjson>=3.10.18
Requires-Dist: pydantic-settings>=2.8.1
Requires-Dist: rich>=14.0.0
Requires-Dist: structlog>=25.2.0
